{
  "kamisato_ayaka": {
    "weapons": [
      "mistsplitter_reforged",
      "amenoma_kageuchi",
      "primordial_jade_cutter"
    ],
    "artifacts": [
      ["blizzard_strayer"],
      ["blizzard_strayer", "gladiators_finale"]
    ]
  },
  "jean": {
    "weapons": ["favonius_sword", "amenoma_kageuchi", "dull_blade"],
    "artifacts": [
      ["viridescent_venerer"],
      ["gladiators_finale", "viridescent_venerer"]
    ]
  },
  "traveler": {
    "weapons": ["favonius_sword", "prototype_rancour", "dull_blade"],
    "artifacts": [
      ["emblem_of_severed_fate"],
      ["deepwood_memories"]
    ]
  },
  "lisa": {
    "weapons": ["apprentices_notes", "eye_of_perception", "favonius_codex"],
    "artifacts": [
      ["wanderers_troupe"],
      ["instructor"],
      ["emblem_of_severed_fate"]
    ]
  },
  "barbara": {
    "weapons": [
      "thrilling_tales_of_dragon_slayers",
      "prototype_amber",
      "apprentices_notes"
    ],
    "artifacts": [["maiden_beloved"], ["oceanhued_clam"], ["maiden_beloved"]]
  },
  "kaeya": {
    "weapons": ["dull_blade", "favonius_sword", "prototype_rancour"],
    "artifacts": [
      ["blizzard_strayer"],
      ["emblem_of_severed_fate"]
    ]
  },
  "diluc": {
    "weapons": ["wolfs_gravestone", "serpent_spine", "luxurious_sealord"],
    "artifacts": [
      ["crimson_witch_of_flames"],
      ["gladiators_finale"]
    ]
  },
  "razor": {
    "weapons": ["snowtombed_starsilver", "waster_greatsword", "rainslasher"],
    "artifacts": [["gladiators_finale"], ["gladiators_finale"], ["pale_flame"]]
  },
  "amber": {
    "weapons": ["hunters_bow", "favonius_warbow", "rust"],
    "artifacts": [
      ["wanderers_troupe"],
      ["crimson_witch_of_flames"]
    ]
  },
  "venti": {
    "weapons": ["the_stringless", "elegy_for_the_end", "favonius_warbow"],
    "artifacts": [
      ["viridescent_venerer"],
      ["gladiators_finale", "viridescent_venerer"]
    ]
  },
  "xiangling": {
    "weapons": ["the_catch", "favonius_lance", "dragons_bane"],
    "artifacts": [
      ["emblem_of_severed_fate"],
      ["crimson_witch_of_flames"]
    ]
  },
  "beidou": {
    "weapons": ["waster_greatsword", "rainslasher", "favonius_greatsword"],
    "artifacts": [
      ["emblem_of_severed_fate"],
      ["gladiators_finale"]
    ]
  },
  "xingqiu": {
    "weapons": ["sacrificial_sword", "favonius_sword", "iron_sting"],
    "artifacts": [
      ["noblesse_oblige", "heart_of_depth"],
      ["emblem_of_severed_fate"],
      ["noblesse_oblige"]
    ]
  },
  "xiao": {
    "weapons": ["primordial_jade_wingedspear", "deathmatch", "staff_of_homa"],
    "artifacts": [
      ["vermillion_hereafter"],
      ["gladiators_finale", "viridescent_venerer"],
      ["viridescent_venerer", "shimenawas_reminiscence"]
    ]
  },
  "ningguang": {
    "weapons": ["apprentices_notes", "the_widsith", "solar_pearl"],
    "artifacts": [
      ["gladiators_finale", "archaic_petra"],
      ["archaic_petra"],
      ["gladiators_finale"]
    ]
  },
  "klee": {
    "weapons": [
      "lost_prayer_to_the_sacred_winds",
      "dodoco_tales",
      "the_widsith"
    ],
    "artifacts": [
      ["crimson_witch_of_flames"],
      ["crimson_witch_of_flames"],
      ["wanderers_troupe"]
    ]
  },
  "zhongli": {
    "weapons": ["black_tassel", "deathmatch", "favonius_lance"],
    "artifacts": [
      ["tenacity_of_the_millelith"],
      ["noblesse_oblige", "tenacity_of_the_millelith"],
      ["tenacity_of_the_millelith"]
    ]
  },
  "fischl": {
    "weapons": ["the_stringless", "hunters_bow", "mitternachts_waltz"],
    "artifacts": [
      ["gladiators_finale", "thundering_fury"],
      ["thundering_fury"],
      ["gladiators_finale", "shimenawas_reminiscence"]
    ]
  },
  "bennett": {
    "weapons": ["skyward_blade", "favonius_sword", "aquila_favonia"],
    "artifacts": [["noblesse_oblige"], ["noblesse_oblige"], ["instructor"]]
  },
  "tartaglia": {
    "weapons": ["polar_star", "skyward_harp", "rust"],
    "artifacts": [
      ["gladiators_finale", "heart_of_depth"],
      ["heart_of_depth"],
      ["heart_of_depth", "shimenawas_reminiscence"]
    ]
  },
  "noelle": {
    "weapons": ["whiteblind", "serpent_spine", "waster_greatsword"],
    "artifacts": [
      ["gladiators_finale"],
      ["husk_of_opulent_dreams"],
      ["gladiators_finale"]
    ]
  },
  "qiqi": {
    "weapons": ["sacrificial_sword", "the_flute", "dull_blade"],
    "artifacts": [["oceanhued_clam"], ["maiden_beloved"], ["oceanhued_clam"]]
  },
  "chongyun": {
    "weapons": [
      "sacrificial_greatsword",
      "waster_greatsword",
      "favonius_greatsword"
    ],
    "artifacts": [
      ["blizzard_strayer"],
      ["blizzard_strayer", "noblesse_oblige"]
    ]
  },
  "ganyu": {
    "weapons": ["amos_bow", "hamayumi", "prototype_crescent"],
    "artifacts": [
      ["wanderers_troupe"],
      ["blizzard_strayer"]
    ]
  },
  "albedo": {
    "weapons": ["cinnabar_spindle", "harbinger_of_dawn", "festering_desire"],
    "artifacts": [
      ["husk_of_opulent_dreams"],
      ["archaic_petra"]
    ]
  },
  "diona": {
    "weapons": ["sacrificial_bow", "favonius_warbow", "hunters_bow"],
    "artifacts": [
      ["maiden_beloved"],
      ["maiden_beloved", "tenacity_of_the_millelith"],
      ["noblesse_oblige"]
    ]
  },
  "mona": {
    "weapons": [
      "thrilling_tales_of_dragon_slayers",
      "the_widsith",
      "prototype_amber"
    ],
    "artifacts": [
      ["noblesse_oblige"],
      ["emblem_of_severed_fate"],
      ["instructor"]
    ]
  },
  "keqing": {
    "weapons": ["lions_roar", "the_black_sword", "dull_blade"],
    "artifacts": [
      ["thundering_fury"],
      ["gladiators_finale", "thundering_fury"],
      ["gladiators_finale"]
    ]
  },
  "sucrose": {
    "weapons": [
      "sacrificial_fragments",
      "thrilling_tales_of_dragon_slayers",
      "favonius_codex"
    ],
    "artifacts": [
      ["viridescent_venerer"],
      ["instructor"]
    ]
  },
  "xinyan": {
    "weapons": ["waster_greatsword", "the_bell", "favonius_greatsword"],
    "artifacts": [
      ["gladiators_finale"],
      ["tenacity_of_the_millelith"],
      ["crimson_witch_of_flames"]
    ]
  },
  "rosaria": {
    "weapons": ["favonius_lance", "beginners_protector", "dragonspine_spear"],
    "artifacts": [
      ["noblesse_oblige"],
      ["blizzard_strayer"]
    ]
  },
  "hu_tao": {
    "weapons": ["staff_of_homa", "dragons_bane", "deathmatch"],
    "artifacts": [
      ["crimson_witch_of_flames"],
      ["shimenawas_reminiscence"],
      ["wanderers_troupe", "crimson_witch_of_flames"]
    ]
  },
  "kaedehara_kazuha": {
    "weapons": ["iron_sting", "freedomsworn", "sacrificial_sword"],
    "artifacts": [
      ["viridescent_venerer"],
      ["gladiators_finale", "viridescent_venerer"]
    ]
  },
  "yanfei": {
    "weapons": ["apprentices_notes", "the_widsith", "dodoco_tales"],
    "artifacts": [
      ["wanderers_troupe"],
      ["crimson_witch_of_flames"],
      ["wanderers_troupe"]
    ]
  },
  "yoimiya": {
    "weapons": ["rust", "thundering_pulse", "skyward_harp"],
    "artifacts": [
      ["shimenawas_reminiscence"],
      ["echoes_of_an_offering"]
    ]
  },
  "thoma": {
    "weapons": ["beginners_protector", "black_tassel", "favonius_lance"],
    "artifacts": [
      ["tenacity_of_the_millelith", "emblem_of_severed_fate"],
      ["emblem_of_severed_fate"],
      ["tenacity_of_the_millelith"]
    ]
  },
  "eula": {
    "weapons": ["song_of_broken_pines", "wolfs_gravestone", "serpent_spine"],
    "artifacts": [
      ["pale_flame"],
      ["bloodstained_chivalry", "pale_flame"],
      ["pale_flame"]
    ]
  },
  "raiden_shogun": {
    "weapons": ["engulfing_lightning", "the_catch", "skyward_spine"],
    "artifacts": [
      ["emblem_of_severed_fate"],
      ["gladiators_finale", "emblem_of_severed_fate"]
    ]
  },
  "sayu": {
    "weapons": [
      "sacrificial_greatsword",
      "waster_greatsword",
      "luxurious_sealord"
    ],
    "artifacts": [
      ["viridescent_venerer"],
      ["maiden_beloved"]
    ]
  },
  "sangonomiya_kokomi": {
    "weapons": [
      "prototype_amber",
      "thrilling_tales_of_dragon_slayers",
      "everlasting_moonglow"
    ],
    "artifacts": [
      ["oceanhued_clam"],
      ["tenacity_of_the_millelith"],
      ["maiden_beloved"]
    ]
  },
  "gorou": {
    "weapons": ["hunters_bow", "favonius_warbow", "sacrificial_bow"],
    "artifacts": [
      ["husk_of_opulent_dreams"],
      ["emblem_of_severed_fate", "husk_of_opulent_dreams"]
    ]
  },
  "kujou_sara": {
    "weapons": ["hunters_bow", "fading_twilight", "skyward_harp"],
    "artifacts": [
      ["emblem_of_severed_fate"],
      ["noblesse_oblige"]
    ]
  },
  "arataki_itto": {
    "weapons": ["serpent_spine", "redhorn_stonethresher", "whiteblind"],
    "artifacts": [
      ["husk_of_opulent_dreams"],
      ["gladiators_finale"]
    ]
  },
  "yae_miko": {
    "weapons": ["kaguras_verity", "the_widsith", "skyward_atlas"],
    "artifacts": [
      ["gladiators_finale", "shimenawas_reminiscence"],
      ["gladiators_finale", "thundering_fury"],
      ["gladiators_finale", "wanderers_troupe"]
    ]
  },
  "shikanoin_heizou": {
    "weapons": ["apprentices_notes", "the_widsith", "solar_pearl"],
    "artifacts": [
      ["viridescent_venerer"],
      ["gladiators_finale", "viridescent_venerer"]
    ]
  },
  "yelan": {
    "weapons": ["favonius_warbow", "aqua_simulacra", "elegy_for_the_end"],
    "artifacts": [
      ["emblem_of_severed_fate"],
      ["noblesse_oblige", "heart_of_depth"],
      ["heart_of_depth", "tenacity_of_the_millelith"]
    ]
  },
  "aloy": {
    "weapons": ["hunters_bow", "rust", "the_stringless"],
    "artifacts": [
      ["blizzard_strayer"],
      ["wanderers_troupe"]
    ]
  },
  "shenhe": {
    "weapons": ["favonius_lance", "skyward_spine", "calamity_queller"],
    "artifacts": [
      ["gladiators_finale", "shimenawas_reminiscence"],
      ["noblesse_oblige"],
      ["gladiators_finale"]
    ]
  },
  "yun_jin": {
    "weapons": ["favonius_lance", "beginners_protector", "kitain_cross_spear"],
    "artifacts": [
      ["husk_of_opulent_dreams"],
      ["emblem_of_severed_fate", "husk_of_opulent_dreams"],
      ["husk_of_opulent_dreams"]
    ]
  },
  "kuki_shinobu": {
    "weapons": ["dull_blade", "iron_sting", "favonius_sword"],
    "artifacts": [
      ["tenacity_of_the_millelith"],
      ["maiden_beloved"]
    ]
  },
  "kamisato_ayato": {
    "weapons": [
      "the_black_sword",
      "haran_geppaku_futsu",
      "primordial_jade_cutter"
    ],
    "artifacts": [
      ["gladiators_finale"],
      ["echoes_of_an_offering"],
      ["heart_of_depth"]
    ]
  },
  "collei": {
    "weapons": ["hunters_bow", "favonius_warbow", "the_stringless"],
    "artifacts": [
      ["deepwood_memories"],
      ["emblem_of_severed_fate"],
      ["deepwood_memories"]
    ]
  },
  "dori": {
    "weapons": ["waster_greatsword", "sacrificial_greatsword", "the_bell"],
    "artifacts": [
      ["noblesse_oblige"],
      ["emblem_of_severed_fate"],
      ["tenacity_of_the_millelith", "emblem_of_severed_fate"]
    ]
  },
  "tighnari": {
    "weapons": ["hunters_path", "skyward_harp", "the_stringless"],
    "artifacts": [
      ["wanderers_troupe"],
      ["gilded_dreams"],
      ["deepwood_memories"]
    ]
  }
}
